{"cameraMode":{"drawMode":0,"name":"Shaded","section":"Shading Mode"},"sceneLighting":true,"audioPlay":false,"sceneViewState":{"showFog":true,"showMaterialUpdate":false,"showSkybox":true,"showFlares":true,"showImageEffects":true,"showParticleSystems":true},"in2DMode":false,"pivot":{"x":-30.709972381591798,"y":93.55998229980469,"z":35.150535583496097},"rotation":{"x":0.3473089933395386,"y":0.5263532400131226,"z":-0.2486741989850998,"w":0.7352736592292786},"size":28.760622024536134,"orthographic":false}